pysentence_similarity/__init__.py
pysentence_similarity/_model.py
pysentence_similarity/_splitter.py
pysentence_similarity/_storage.py
pysentence_similarity/_support_models.py
pysentence_similarity/_version.py
pysentence_similarity/compute.py
pysentence_similarity/pooling.py
pysentence_similarity/version.py
pysentence_similarity/utils/__init__.py
pysentence_similarity/utils/_compute_score.py
pysentence_similarity/utils/_search_similar.py
tests/__init__.py
tests/test_compute.py
tests/test_model.py
tests/test_splitter.py
tests/test_storage.py
tests/test_utils.py
pysentence_similarity-1.0.1.dist-info/LICENSE
pysentence_similarity-1.0.1.dist-info/METADATA
pysentence_similarity-1.0.1.dist-info/WHEEL
pysentence_similarity-1.0.1.dist-info/top_level.txt
pysentence_similarity-1.0.1.dist-info/RECORD
