Metadata-Version: 2.1
Name: pysentence-similarity
Version: 1.0.1
Summary: PySentence-Similarity is a tool designed to identify and find similarities between sentences and a base sentence, expressed as a percentage.
Home-page: https://github.com/goldpulpy/pysentence-similarity
Author: goldpulpy
Author-email: sawsani1928@gmail.com
License: UNKNOWN
Project-URL: Documentation, https://github.com/goldpulpy/pysentence-similarity#readme
Project-URL: Issues, https://github.com/goldpulpy/pysentence-similarity/issues
Project-URL: Homepage, https://github.com/goldpulpy/pysentence-similarity
Keywords: sentence similarity NLP natural language processing
Platform: UNKNOWN
Classifier: Programming Language :: Python :: 3
Classifier: License :: OSI Approved :: MIT License
Classifier: Operating System :: OS Independent
Classifier: Natural Language :: English
Classifier: Topic :: Software Development :: Libraries :: Python Modules
Classifier: Intended Audience :: Developers
Requires-Python: >=3.8
License-File: LICENSE
Requires-Dist: beautifulsoup4
Requires-Dist: h5py
Requires-Dist: onnxruntime-gpu
Requires-Dist: platformdirs
Requires-Dist: tokenizers
